ez_setup.py
setup.py
examples/fifosample.py
examples/forging.py
examples/sample.py
examples/timesample.py
examples/buddyremove/index.html
examples/buddyremove/remove.py
pyahoolib.egg-info/PKG-INFO
pyahoolib.egg-info/SOURCES.txt
pyahoolib.egg-info/dependency_links.txt
pyahoolib.egg-info/top_level.txt
yahoo/__init__.py
yahoo/auth.py
yahoo/ch.py
yahoo/consts.py
yahoo/cr.py
yahoo/packet.py
yahoo/py_sha.py
yahoo/session.py
