Metadata-Version: 1.0
Name: pyahoolib
Version: 0.2
Summary: Module implementing the yahoo messenger protocol.
Home-page: UNKNOWN
Author: Maries Ionel Cristian
Author-email: ionel dot mc at gmail dot com
License: UNKNOWN
Platform: UNKNOWN
Classifier: Development Status :: 3 - Alpha
Classifier: Intended Audience :: Developers
Classifier: Intended Audience :: System Administrators
Classifier: License :: OSI Approved :: MIT License
Classifier: Operating System :: Microsoft :: Windows
Classifier: Operating System :: POSIX
Classifier: Programming Language :: Python
Classifier: Topic :: System :: Networking
